automapdb/__init__.py
automapdb/cli.py
automapdb/db.py
automapdb/manager.py
automapdb/mapper.py
automapdb/utils.py
AutoMapDB-0.1.5.dist-info/LICENSE
AutoMapDB-0.1.5.dist-info/METADATA
AutoMapDB-0.1.5.dist-info/WHEEL
AutoMapDB-0.1.5.dist-info/entry_points.txt
AutoMapDB-0.1.5.dist-info/top_level.txt
AutoMapDB-0.1.5.dist-info/RECORD
