Metadata-Version: 2.1
Name: AutoMapDB
Version: 0.1.5
Summary: Automagically provides CRUD API to any PostgreSQL database
Home-page: https://gitlab.com/mds-imbi-freiburg/automapdb
Author: Fabi T.
Author-email: fabian.thomczyk@uniklinik-freiburg.de
License: License :: MIT License
Classifier: Programming Language :: Python :: 3
Classifier: Programming Language :: Python :: 3.6
Classifier: Programming Language :: Python :: 3.10
Requires-Python: >=3.6, <=3.11
License-File: LICENSE
Requires-Dist: psycopg2
Requires-Dist: fire
Requires-Dist: pyyaml (==5.1)
